{
  "id": 868,
  "filename": "invoice_868.pdf",
  "layout_style": "two_tone",
  "page_size": "letter",
  "complexity_tier": "simple",
  "color_palette_index": 9,
  "invoice_number": "076248",
  "issue_date": "2022-09-30",
  "due_date": "October 14 2022",
  "payment_terms": "Net 30",
  "currency": "AUD",
  "currency_symbol": "A$",
  "po_number": "PO-51168",
  "seller_name": "Pacific Rim Exports",
  "seller_address": "88 Harbour Road Hong Kong",
  "seller_email": "accounts@pacificrimexports.hk",
  "seller_phone": "+852 2100 0000",
  "seller_tax_id": "BR No: 12345678",
  "client_name": "Sunrise Academy",
  "client_address": "10 Scholar Way Singapore 188064",
  "client_email": "finance@sunriseacademy.edu.sg",
  "num_line_items": 2,
  "line_items": [
    {
      "description": "Training Workshop",
      "unit": "person",
      "quantity": 10,
      "unit_price": 756.03,
      "discount_pct": 0,
      "line_total": 7560.3
    },
    {
      "description": "Tech Writing",
      "unit": "pg",
      "quantity": 5,
      "unit_price": 200.82,
      "discount_pct": 0,
      "line_total": 1004.1
    }
  ],
  "subtotal": 8564.4,
  "tax_label": "VAT 21pct",
  "tax_rate_pct": 21.0,
  "tax_amount": 1798.52,
  "shipping_amount": 0.0,
  "total_due": 10362.92,
  "notes": "Please retain this invoice for your accounting records.",
  "bank_details": {
    "Bank": "Westpac",
    "BSB": "032-000",
    "Account": "123456",
    "SWIFT": "WPACAU2S"
  },
  "has_logo": true,
  "has_discount_column": false,
  "has_unit_column": true,
  "has_notes": true,
  "has_bank_details": true,
  "has_shipping": false,
  "has_po_number": true,
  "has_tax": true
}