{
  "id": 936,
  "filename": "invoice_936.pdf",
  "layout_style": "minimal",
  "page_size": "A4",
  "complexity_tier": "simple",
  "color_palette_index": 4,
  "invoice_number": "2025-73686",
  "issue_date": "08-Dec-2022",
  "due_date": "2022-12-23",
  "payment_terms": "50% upfront balance on delivery",
  "currency": "AUD",
  "currency_symbol": "A$",
  "po_number": null,
  "seller_name": "Sunrise Digital Agency",
  "seller_address": "12F 88 Queensway Admiralty Hong Kong",
  "seller_email": "hello@sunrisedigital.hk",
  "seller_phone": "+852 3100 0000",
  "seller_tax_id": "BR No: 98765432",
  "client_name": "GoldenGate Financial",
  "client_address": "101 Market St San Francisco CA 94105 USA",
  "client_email": "invoices@goldengatefin.com",
  "num_line_items": 1,
  "line_items": [
    {
      "description": "Brand Identity",
      "unit": "ea",
      "quantity": 1,
      "unit_price": 5017.43,
      "discount_pct": 0,
      "line_total": 5017.43
    }
  ],
  "subtotal": 5017.43,
  "tax_label": "HST 13pct",
  "tax_rate_pct": 13.0,
  "tax_amount": 652.27,
  "shipping_amount": 0.0,
  "total_due": 5669.7,
  "notes": null,
  "bank_details": null,
  "has_logo": true,
  "has_discount_column": false,
  "has_unit_column": true,
  "has_notes": false,
  "has_bank_details": false,
  "has_shipping": false,
  "has_po_number": false,
  "has_tax": true
}