{
  "id": 534,
  "filename": "invoice_534.pdf",
  "layout_style": "classic",
  "page_size": "A4",
  "complexity_tier": "complex",
  "color_palette_index": 7,
  "invoice_number": "BILL-2022-18125",
  "issue_date": "31-Mar-2022",
  "due_date": "14 April 2022",
  "payment_terms": "Net 60",
  "currency": "CAD",
  "currency_symbol": "CA$",
  "po_number": "PO-48639",
  "seller_name": "Tesseract Labs",
  "seller_address": "2001 Infinite Loop Cupertino CA 95014 USA",
  "seller_email": "billing@tesseractlabs.com",
  "seller_phone": "+1 408-555-0201",
  "seller_tax_id": "EIN: 77-8901234",
  "client_name": "The Grand Brasserie Group",
  "client_address": "15 Rue Montorgueil 75001 Paris France",
  "client_email": "comptabilite@grandbrasserie.fr",
  "num_line_items": 9,
  "line_items": [
    {
      "description": "Cloud Hosting",
      "unit": "mo",
      "quantity": 50,
      "unit_price": 859.13,
      "discount_pct": 5,
      "line_total": 40808.67
    },
    {
      "description": "Accounting Services",
      "unit": "mo",
      "quantity": 1,
      "unit_price": 505.7,
      "discount_pct": 0,
      "line_total": 505.7
    },
    {
      "description": "Software Dev",
      "unit": "hr",
      "quantity": 1,
      "unit_price": 137.78,
      "discount_pct": 0,
      "line_total": 137.78
    },
    {
      "description": "IT Support",
      "unit": "hr",
      "quantity": 1,
      "unit_price": 94.32,
      "discount_pct": 0,
      "line_total": 94.32
    },
    {
      "description": "Equipment Rental",
      "unit": "day",
      "quantity": 1,
      "unit_price": 852.06,
      "discount_pct": 20,
      "line_total": 681.65
    },
    {
      "description": "Consulting Day Rate",
      "unit": "day",
      "quantity": 5,
      "unit_price": 3851.53,
      "discount_pct": 0,
      "line_total": 19257.65
    },
    {
      "description": "Office Supplies",
      "unit": "lot",
      "quantity": 1,
      "unit_price": 1273.12,
      "discount_pct": 15,
      "line_total": 1082.15
    },
    {
      "description": "Catering Services",
      "unit": "head",
      "quantity": 2,
      "unit_price": 44.1,
      "discount_pct": 0,
      "line_total": 88.2
    },
    {
      "description": "Community Mgmt",
      "unit": "mo",
      "quantity": 25,
      "unit_price": 1535.47,
      "discount_pct": 20,
      "line_total": 30709.4
    }
  ],
  "subtotal": 93365.52,
  "tax_label": "HST 13pct",
  "tax_rate_pct": 13.0,
  "tax_amount": 12137.52,
  "shipping_amount": 0.0,
  "total_due": 105503.04,
  "notes": "Goods remain property of seller until full payment received.",
  "bank_details": null,
  "has_logo": true,
  "has_discount_column": false,
  "has_unit_column": true,
  "has_notes": true,
  "has_bank_details": false,
  "has_shipping": false,
  "has_po_number": true,
  "has_tax": true
}