{
  "id": 749,
  "filename": "invoice_749.pdf",
  "layout_style": "two_tone",
  "page_size": "A4",
  "complexity_tier": "medium",
  "color_palette_index": 12,
  "invoice_number": "2025-60730",
  "issue_date": "31-Aug-2022",
  "due_date": "2022-09-15",
  "payment_terms": "Cash on Delivery",
  "currency": "HKD",
  "currency_symbol": "HK$",
  "po_number": "PO-13565",
  "seller_name": "Pacific Rim Exports",
  "seller_address": "88 Harbour Road Hong Kong",
  "seller_email": "accounts@pacificrimexports.hk",
  "seller_phone": "+852 2100 0000",
  "seller_tax_id": "BR No: 12345678",
  "client_name": "Brightside Retailers",
  "client_address": "99 Commerce Blvd Austin TX 78701 USA",
  "client_email": "ap@brightsideretail.com",
  "num_line_items": 4,
  "line_items": [
    {
      "description": "Data Analysis",
      "unit": "ea",
      "quantity": 3,
      "unit_price": 1659.94,
      "discount_pct": 5,
      "line_total": 4730.83
    },
    {
      "description": "Event Management",
      "unit": "ea",
      "quantity": 1,
      "unit_price": 10344.2,
      "discount_pct": 0,
      "line_total": 10344.2
    },
    {
      "description": "Security Services",
      "unit": "day",
      "quantity": 1,
      "unit_price": 747.85,
      "discount_pct": 0,
      "line_total": 747.85
    },
    {
      "description": "Community Mgmt",
      "unit": "mo",
      "quantity": 3,
      "unit_price": 2187.69,
      "discount_pct": 10,
      "line_total": 5906.76
    }
  ],
  "subtotal": 21729.64,
  "tax_label": "Service Tax 6pct",
  "tax_rate_pct": 6.0,
  "tax_amount": 1303.78,
  "shipping_amount": 0.0,
  "total_due": 23033.42,
  "notes": "Thank you for your business. We value our long-term partnership.",
  "bank_details": {
    "Bank": "Chase Bank",
    "Account": "1234567890",
    "Routing": "021000021",
    "SWIFT": "CHASUS33"
  },
  "has_logo": true,
  "has_discount_column": true,
  "has_unit_column": true,
  "has_notes": true,
  "has_bank_details": true,
  "has_shipping": false,
  "has_po_number": true,
  "has_tax": true
}