{
  "id": 661,
  "filename": "invoice_661.pdf",
  "layout_style": "classic",
  "page_size": "A4",
  "complexity_tier": "complex",
  "color_palette_index": 12,
  "invoice_number": "BILL71389",
  "issue_date": "07-Feb-2024",
  "due_date": "07/04/2024",
  "payment_terms": "Net 30",
  "currency": "NOK",
  "currency_symbol": "kr",
  "po_number": null,
  "seller_name": "Mirage Productions FZ-LLC",
  "seller_address": "Dubai Studio City Dubai UAE",
  "seller_email": "accounts@mirageproductions.ae",
  "seller_phone": "+971 4 444 0199",
  "seller_tax_id": "TRN: 100987654321003",
  "client_name": "Evergreen International School",
  "client_address": "21 Buona Vista Rd Singapore 275720",
  "client_email": "finance@evergreenintl.edu.sg",
  "num_line_items": 9,
  "line_items": [
    {
      "description": "Accounting Services",
      "unit": "mo",
      "quantity": 5,
      "unit_price": 839.19,
      "discount_pct": 20,
      "line_total": 3356.76
    },
    {
      "description": "Software Dev",
      "unit": "hr",
      "quantity": 25,
      "unit_price": 100.19,
      "discount_pct": 0,
      "line_total": 2504.75
    },
    {
      "description": "Training Workshop",
      "unit": "person",
      "quantity": 1,
      "unit_price": 622.05,
      "discount_pct": 5,
      "line_total": 590.95
    },
    {
      "description": "Catering Services",
      "unit": "head",
      "quantity": 2,
      "unit_price": 52.02,
      "discount_pct": 0,
      "line_total": 104.04
    },
    {
      "description": "Video Production",
      "unit": "ea",
      "quantity": 1,
      "unit_price": 2717.55,
      "discount_pct": 0,
      "line_total": 2717.55
    },
    {
      "description": "Equipment Rental",
      "unit": "day",
      "quantity": 25,
      "unit_price": 344.69,
      "discount_pct": 5,
      "line_total": 8186.39
    },
    {
      "description": "IT Support",
      "unit": "hr",
      "quantity": 2,
      "unit_price": 182.37,
      "discount_pct": 5,
      "line_total": 346.5
    },
    {
      "description": "Event Management",
      "unit": "ea",
      "quantity": 25,
      "unit_price": 7740.25,
      "discount_pct": 0,
      "line_total": 193506.25
    },
    {
      "description": "Bookkeeping",
      "unit": "mo",
      "quantity": 50,
      "unit_price": 1097.58,
      "discount_pct": 5,
      "line_total": 52135.05
    }
  ],
  "subtotal": 263448.24,
  "tax_label": "Service Tax 6pct",
  "tax_rate_pct": 6.0,
  "tax_amount": 15806.89,
  "shipping_amount": 185.19,
  "total_due": 279440.32,
  "notes": null,
  "bank_details": {
    "Bank": "Emirates NBD",
    "IBAN": "AE070331234567890123456",
    "SWIFT": "EBILAEAD"
  },
  "has_logo": true,
  "has_discount_column": false,
  "has_unit_column": false,
  "has_notes": false,
  "has_bank_details": true,
  "has_shipping": true,
  "has_po_number": false,
  "has_tax": true
}