{
  "id": 756,
  "filename": "invoice_756.pdf",
  "layout_style": "ledger",
  "page_size": "A4",
  "complexity_tier": "complex",
  "color_palette_index": 5,
  "invoice_number": "054282",
  "issue_date": "05/25/2024",
  "due_date": "2024-06-09",
  "payment_terms": "Net 30",
  "currency": "HKD",
  "currency_symbol": "HK$",
  "po_number": "PO-82476",
  "seller_name": "IronCore Manufacturing",
  "seller_address": "77 Steel Drive Pittsburgh PA 15201 USA",
  "seller_email": "ar@ironcoremfg.com",
  "seller_phone": "+1 412-555-0177",
  "seller_tax_id": "EIN: 45-6789012",
  "client_name": "ClearSky Airlines",
  "client_address": "Terminal 5 Heathrow London TW6 1QG UK",
  "client_email": "procurement@clearskyair.com",
  "num_line_items": 12,
  "line_items": [
    {
      "description": "Mobile App Dev",
      "unit": "ea",
      "quantity": 3,
      "unit_price": 5000.5,
      "discount_pct": 10,
      "line_total": 13501.35
    },
    {
      "description": "Raw Materials",
      "unit": "kg",
      "quantity": 5,
      "unit_price": 72.48,
      "discount_pct": 5,
      "line_total": 344.28
    },
    {
      "description": "Catering Services",
      "unit": "head",
      "quantity": 50,
      "unit_price": 34.71,
      "discount_pct": 20,
      "line_total": 1388.4
    },
    {
      "description": "iOS App Dev",
      "unit": "ea",
      "quantity": 10,
      "unit_price": 6444.71,
      "discount_pct": 20,
      "line_total": 51557.68
    },
    {
      "description": "Managed Cloud",
      "unit": "mo",
      "quantity": 5,
      "unit_price": 2051.85,
      "discount_pct": 10,
      "line_total": 9233.33
    },
    {
      "description": "Video Production",
      "unit": "ea",
      "quantity": 10,
      "unit_price": 3946.63,
      "discount_pct": 15,
      "line_total": 33546.36
    },
    {
      "description": "Translation Services",
      "unit": "pg",
      "quantity": 25,
      "unit_price": 34.72,
      "discount_pct": 15,
      "line_total": 737.8
    },
    {
      "description": "Architecture Fees",
      "unit": "ea",
      "quantity": 1,
      "unit_price": 9745.19,
      "discount_pct": 0,
      "line_total": 9745.19
    },
    {
      "description": "Security Services",
      "unit": "day",
      "quantity": 1,
      "unit_price": 966.9,
      "discount_pct": 10,
      "line_total": 870.21
    },
    {
      "description": "Accounting Services",
      "unit": "mo",
      "quantity": 2,
      "unit_price": 543.64,
      "discount_pct": 0,
      "line_total": 1087.28
    },
    {
      "description": "Export Documentation",
      "unit": "ea",
      "quantity": 5,
      "unit_price": 148.85,
      "discount_pct": 20,
      "line_total": 595.4
    },
    {
      "description": "Maintenance Contract",
      "unit": "mo",
      "quantity": 1,
      "unit_price": 1037.06,
      "discount_pct": 10,
      "line_total": 933.35
    }
  ],
  "subtotal": 123540.63,
  "tax_label": "VAT 19pct",
  "tax_rate_pct": 19.0,
  "tax_amount": 23472.72,
  "shipping_amount": 29.1,
  "total_due": 147042.45,
  "notes": "Please direct billing queries to our accounts department.",
  "bank_details": null,
  "has_logo": true,
  "has_discount_column": false,
  "has_unit_column": false,
  "has_notes": true,
  "has_bank_details": false,
  "has_shipping": true,
  "has_po_number": true,
  "has_tax": true
}