{
  "id": 265,
  "filename": "invoice_265.pdf",
  "layout_style": "bold_header",
  "page_size": "A4",
  "complexity_tier": "medium",
  "color_palette_index": 2,
  "invoice_number": "INV-32580",
  "issue_date": "08/20/2024",
  "due_date": "2024-09-04",
  "payment_terms": "Upon completion",
  "currency": "HKD",
  "currency_symbol": "HK$",
  "po_number": null,
  "seller_name": "Cobalt Digital Studio",
  "seller_address": "9F Tower 2 Times Square Causeway Bay HK",
  "seller_email": "studio@cobaltdigital.hk",
  "seller_phone": "+852 3900 1111",
  "seller_tax_id": "BR No: 11223344",
  "client_name": "SkyBridge Aviation PLC",
  "client_address": "Waterside Harmondsworth UB7 0GB UK",
  "client_email": "procurement@skybridgeav.com",
  "num_line_items": 4,
  "line_items": [
    {
      "description": "Office Supplies",
      "unit": "lot",
      "quantity": 2,
      "unit_price": 137.56,
      "discount_pct": 5,
      "line_total": 261.36
    },
    {
      "description": "Video Production",
      "unit": "ea",
      "quantity": 50,
      "unit_price": 2673.03,
      "discount_pct": 10,
      "line_total": 120286.35
    },
    {
      "description": "Manufacturing Parts",
      "unit": "lot",
      "quantity": 1,
      "unit_price": 7045.35,
      "discount_pct": 10,
      "line_total": 6340.82
    },
    {
      "description": "Architecture Fees",
      "unit": "ea",
      "quantity": 1,
      "unit_price": 12751.55,
      "discount_pct": 0,
      "line_total": 12751.55
    }
  ],
  "subtotal": 139640.08,
  "tax_label": "HST 13pct",
  "tax_rate_pct": 13.0,
  "tax_amount": 18153.21,
  "shipping_amount": 0.0,
  "total_due": 157793.29,
  "notes": null,
  "bank_details": {
    "Bank": "Barclays Bank",
    "Sort Code": "20-00-01",
    "Account": "87654321",
    "IBAN": "GB12BARC20000187654321"
  },
  "has_logo": true,
  "has_discount_column": true,
  "has_unit_column": false,
  "has_notes": false,
  "has_bank_details": true,
  "has_shipping": false,
  "has_po_number": false,
  "has_tax": true
}