{
  "id": 101,
  "filename": "invoice_101.pdf",
  "layout_style": "formal",
  "page_size": "A4",
  "complexity_tier": "complex",
  "color_palette_index": 1,
  "invoice_number": "PROFORMA-2024-26578",
  "issue_date": "10/17/2024",
  "due_date": "12/16/2024",
  "payment_terms": "Net 15",
  "currency": "AED",
  "currency_symbol": "AED",
  "po_number": "PO-98676",
  "seller_name": "Desert Bloom LLC",
  "seller_address": "9001 E Camelback Rd Scottsdale AZ 85251 USA",
  "seller_email": "invoices@desertbloom.com",
  "seller_phone": "+1 480-555-0144",
  "seller_tax_id": "EIN: 98-7654321",
  "client_name": "SkyBridge Aviation PLC",
  "client_address": "Waterside Harmondsworth UB7 0GB UK",
  "client_email": "procurement@skybridgeav.com",
  "num_line_items": 14,
  "line_items": [
    {
      "description": "Manufacturing Parts",
      "unit": "lot",
      "quantity": 2,
      "unit_price": 1908.31,
      "discount_pct": 20,
      "line_total": 3053.3
    },
    {
      "description": "Mobile App Dev",
      "unit": "ea",
      "quantity": 2,
      "unit_price": 2919.52,
      "discount_pct": 15,
      "line_total": 4963.18
    },
    {
      "description": "Translation Services",
      "unit": "pg",
      "quantity": 5,
      "unit_price": 138.06,
      "discount_pct": 5,
      "line_total": 655.78
    },
    {
      "description": "Software License",
      "unit": "seat",
      "quantity": 3,
      "unit_price": 2450.6,
      "discount_pct": 0,
      "line_total": 7351.8
    },
    {
      "description": "Web Development",
      "unit": "hrs",
      "quantity": 50,
      "unit_price": 233.65,
      "discount_pct": 0,
      "line_total": 11682.5
    },
    {
      "description": "IT Support",
      "unit": "hr",
      "quantity": 1,
      "unit_price": 109.5,
      "discount_pct": 0,
      "line_total": 109.5
    },
    {
      "description": "Software Dev",
      "unit": "hr",
      "quantity": 1,
      "unit_price": 190.62,
      "discount_pct": 0,
      "line_total": 190.62
    },
    {
      "description": "Freight Forwarding",
      "unit": "shpt",
      "quantity": 1,
      "unit_price": 1960.96,
      "discount_pct": 0,
      "line_total": 1960.96
    },
    {
      "description": "Community Mgmt",
      "unit": "mo",
      "quantity": 1,
      "unit_price": 2253.91,
      "discount_pct": 15,
      "line_total": 1915.82
    },
    {
      "description": "Architecture Fees",
      "unit": "ea",
      "quantity": 10,
      "unit_price": 43962.85,
      "discount_pct": 0,
      "line_total": 439628.5
    },
    {
      "description": "Contract Review",
      "unit": "hr",
      "quantity": 1,
      "unit_price": 386.28,
      "discount_pct": 20,
      "line_total": 309.02
    },
    {
      "description": "Bookkeeping",
      "unit": "mo",
      "quantity": 10,
      "unit_price": 898.27,
      "discount_pct": 0,
      "line_total": 8982.7
    },
    {
      "description": "Market Research",
      "unit": "ea",
      "quantity": 2,
      "unit_price": 13583.23,
      "discount_pct": 0,
      "line_total": 27166.46
    },
    {
      "description": "Event Management",
      "unit": "ea",
      "quantity": 10,
      "unit_price": 9007.4,
      "discount_pct": 5,
      "line_total": 85570.3
    }
  ],
  "subtotal": 593540.44,
  "tax_label": "HST 13pct",
  "tax_rate_pct": 13.0,
  "tax_amount": 77160.26,
  "shipping_amount": 0.0,
  "total_due": 670700.7,
  "notes": "Our standard warranty terms apply to all goods and services.",
  "bank_details": {
    "Bank": "Chase Bank",
    "Account": "1234567890",
    "Routing": "021000021",
    "SWIFT": "CHASUS33"
  },
  "has_logo": true,
  "has_discount_column": true,
  "has_unit_column": false,
  "has_notes": true,
  "has_bank_details": true,
  "has_shipping": false,
  "has_po_number": true,
  "has_tax": true
}