{
  "id": 112,
  "filename": "invoice_112.pdf",
  "layout_style": "sidebar",
  "page_size": "letter",
  "complexity_tier": "medium",
  "color_palette_index": 12,
  "invoice_number": "SI61839",
  "issue_date": "2023-05-11",
  "due_date": "May 25 2023",
  "payment_terms": "Immediate",
  "currency": "HKD",
  "currency_symbol": "HK$",
  "po_number": null,
  "seller_name": "Greenleaf Organics",
  "seller_address": "Farm Road 7 Burlington VT 05401 USA",
  "seller_email": "orders@greenleaforganics.com",
  "seller_phone": "+1 802-555-0133",
  "seller_tax_id": "EIN: 23-4567890",
  "client_name": "Luxe Fashion Collective",
  "client_address": "550 Seventh Ave New York NY 10018 USA",
  "client_email": "ap@luxefashion.com",
  "num_line_items": 3,
  "line_items": [
    {
      "description": "Brand Identity",
      "unit": "ea",
      "quantity": 25,
      "unit_price": 3716.58,
      "discount_pct": 0,
      "line_total": 92914.5
    },
    {
      "description": "Training Workshop",
      "unit": "person",
      "quantity": 10,
      "unit_price": 846.04,
      "discount_pct": 0,
      "line_total": 8460.4
    },
    {
      "description": "Content Writing",
      "unit": "pg",
      "quantity": 2,
      "unit_price": 80.02,
      "discount_pct": 0,
      "line_total": 160.04
    }
  ],
  "subtotal": 101534.94,
  "tax_label": "GST 10pct",
  "tax_rate_pct": 10.0,
  "tax_amount": 10153.49,
  "shipping_amount": 0.0,
  "total_due": 111688.43,
  "notes": null,
  "bank_details": {
    "Bank": "Westpac",
    "BSB": "032-000",
    "Account": "123456",
    "SWIFT": "WPACAU2S"
  },
  "has_logo": true,
  "has_discount_column": false,
  "has_unit_column": true,
  "has_notes": false,
  "has_bank_details": true,
  "has_shipping": false,
  "has_po_number": false,
  "has_tax": true
}