{
  "id": 131,
  "filename": "invoice_131.pdf",
  "layout_style": "compact",
  "page_size": "A4",
  "complexity_tier": "very_complex",
  "color_palette_index": 12,
  "invoice_number": "067754",
  "issue_date": "27 October 2022",
  "due_date": "2023-01-25",
  "payment_terms": "Upon completion",
  "currency": "HKD",
  "currency_symbol": "HK$",
  "po_number": "PO-69513",
  "seller_name": "Nordic Craft AB",
  "seller_address": "Kungsgatan 12 111 35 Stockholm Sweden",
  "seller_email": "faktura@nordiccraft.se",
  "seller_phone": "+46 8 555 0100",
  "seller_tax_id": "Org.nr: 556123-4567",
  "client_name": "Quantum Dynamics Corp",
  "client_address": "1000 Innovation Pkwy Cambridge MA 02139 USA",
  "client_email": "accounts@quantumdynamics.com",
  "num_line_items": 24,
  "line_items": [
    {
      "description": "Office Supplies",
      "unit": "lot",
      "quantity": 3,
      "unit_price": 493.57,
      "discount_pct": 0,
      "line_total": 1480.71
    },
    {
      "description": "Software License",
      "unit": "seat",
      "quantity": 50,
      "unit_price": 3061.56,
      "discount_pct": 10,
      "line_total": 137770.2
    },
    {
      "description": "Content Writing",
      "unit": "pg",
      "quantity": 3,
      "unit_price": 166.05,
      "discount_pct": 0,
      "line_total": 498.15
    },
    {
      "description": "Consulting Day Rate",
      "unit": "day",
      "quantity": 1,
      "unit_price": 3079.95,
      "discount_pct": 0,
      "line_total": 3079.95
    },
    {
      "description": "Logo Design",
      "unit": "ea",
      "quantity": 5,
      "unit_price": 2359.01,
      "discount_pct": 0,
      "line_total": 11795.05
    },
    {
      "description": "Mobile App Dev",
      "unit": "ea",
      "quantity": 10,
      "unit_price": 6490.03,
      "discount_pct": 10,
      "line_total": 58410.27
    },
    {
      "description": "Cloud Hosting",
      "unit": "mo",
      "quantity": 1,
      "unit_price": 993.25,
      "discount_pct": 0,
      "line_total": 993.25
    },
    {
      "description": "Social Media Mgmt",
      "unit": "mo",
      "quantity": 1,
      "unit_price": 1282.29,
      "discount_pct": 0,
      "line_total": 1282.29
    },
    {
      "description": "Video Production",
      "unit": "ea",
      "quantity": 25,
      "unit_price": 1747.52,
      "discount_pct": 0,
      "line_total": 43688.0
    },
    {
      "description": "Catering Services",
      "unit": "head",
      "quantity": 1,
      "unit_price": 96.62,
      "discount_pct": 0,
      "line_total": 96.62
    },
    {
      "description": "Architecture Fees",
      "unit": "ea",
      "quantity": 25,
      "unit_price": 22808.9,
      "discount_pct": 0,
      "line_total": 570222.5
    },
    {
      "description": "BI Reporting",
      "unit": "ea",
      "quantity": 1,
      "unit_price": 2938.25,
      "discount_pct": 0,
      "line_total": 2938.25
    },
    {
      "description": "Managed Cloud",
      "unit": "mo",
      "quantity": 10,
      "unit_price": 728.51,
      "discount_pct": 0,
      "line_total": 7285.1
    },
    {
      "description": "Legal Consultation",
      "unit": "hr",
      "quantity": 50,
      "unit_price": 518.46,
      "discount_pct": 20,
      "line_total": 20738.4
    },
    {
      "description": "Security Services",
      "unit": "day",
      "quantity": 1,
      "unit_price": 697.34,
      "discount_pct": 0,
      "line_total": 697.34
    },
    {
      "description": "Community Mgmt",
      "unit": "mo",
      "quantity": 10,
      "unit_price": 1761.27,
      "discount_pct": 10,
      "line_total": 15851.43
    },
    {
      "description": "Software Dev",
      "unit": "hr",
      "quantity": 2,
      "unit_price": 150.53,
      "discount_pct": 0,
      "line_total": 301.06
    },
    {
      "description": "Data Analysis",
      "unit": "ea",
      "quantity": 1,
      "unit_price": 2179.23,
      "discount_pct": 20,
      "line_total": 1743.38
    },
    {
      "description": "Maintenance Contract",
      "unit": "mo",
      "quantity": 25,
      "unit_price": 1843.82,
      "discount_pct": 0,
      "line_total": 46095.5
    },
    {
      "description": "SEO Optimization",
      "unit": "ea",
      "quantity": 1,
      "unit_price": 2900.68,
      "discount_pct": 0,
      "line_total": 2900.68
    },
    {
      "description": "Accounting Services",
      "unit": "mo",
      "quantity": 1,
      "unit_price": 200.28,
      "discount_pct": 20,
      "line_total": 160.22
    },
    {
      "description": "Bookkeeping",
      "unit": "mo",
      "quantity": 1,
      "unit_price": 1338.31,
      "discount_pct": 0,
      "line_total": 1338.31
    },
    {
      "description": "Market Research",
      "unit": "ea",
      "quantity": 10,
      "unit_price": 2505.36,
      "discount_pct": 10,
      "line_total": 22548.24
    },
    {
      "description": "Web Development",
      "unit": "hrs",
      "quantity": 1,
      "unit_price": 96.62,
      "discount_pct": 5,
      "line_total": 91.79
    }
  ],
  "subtotal": 952006.69,
  "tax_label": "VAT 19pct",
  "tax_rate_pct": 19.0,
  "tax_amount": 180881.27,
  "shipping_amount": 152.1,
  "total_due": 1133040.06,
  "notes": null,
  "bank_details": null,
  "has_logo": true,
  "has_discount_column": false,
  "has_unit_column": false,
  "has_notes": false,
  "has_bank_details": false,
  "has_shipping": true,
  "has_po_number": true,
  "has_tax": true
}